allbymyself/__init__.py
allbymyself/admin.py
allbymyself/apps.py
allbymyself/models.py
allbymyself/path_utils.py
allbymyself/templates/.DS_Store
allbymyself/templates/admin/save_row.html
allbymyself/templates/admin/singleton_change_form.html
allbymyself/templates/admin/singleton_object_history.html
allbymyself/templatetags/__init__.py
allbymyself/templatetags/save_row.py
allbymyself/tests/__init__.py
allbymyself/tests/models.py
allbymyself/tests/tests.py
django_allbymyself-1.0.1.dist-info/LICENSE
django_allbymyself-1.0.1.dist-info/METADATA
django_allbymyself-1.0.1.dist-info/WHEEL
django_allbymyself-1.0.1.dist-info/top_level.txt
django_allbymyself-1.0.1.dist-info/RECORD
